calc_lib/__init__.py
calc_lib/funcoes.py
calc_lib_jonathancastrosilva-0.1.0.dist-info/LICENSE
calc_lib_jonathancastrosilva-0.1.0.dist-info/METADATA
calc_lib_jonathancastrosilva-0.1.0.dist-info/WHEEL
calc_lib_jonathancastrosilva-0.1.0.dist-info/top_level.txt
calc_lib_jonathancastrosilva-0.1.0.dist-info/RECORD
