Metadata-Version: 2.1
Name: calc-lib-jonathancastrosilva
Version: 0.1.0
Summary: Biblioteca de calculadora com operações básicas, potência e raiz.
Author-email: Jonathan Castro Silva <jonathancastrosilva@gmail.com>
License: MIT License
Keywords: calculadora,math,operacoes,python
Classifier: Programming Language :: Python :: 3
Classifier: License :: OSI Approved :: MIT License
Classifier: Operating System :: OS Independent
Requires-Python: >=3.7
License-File: LICENSE
